MANIFEST.in
README.rst
setup.py
dood/__init__.py
dood.egg-info/PKG-INFO
dood.egg-info/SOURCES.txt
dood.egg-info/dependency_links.txt
dood.egg-info/requires.txt
dood.egg-info/top_level.txt