Metadata-Version: 1.0
Name: dood
Version: 0.1.3.dev1
Summary: A simplified API for creating polls on doodle.com.
Home-page: http://github.com/mbr/dood
Author: Marc Brinkmann
Author-email: git@marcbrinkmann.de
License: MIT
Platform: UNKNOWN
